ornamentalist/__init__.py
ornamentalist-2.1.0.dist-info/WHEEL
ornamentalist-2.1.0.dist-info/METADATA
ornamentalist-2.1.0.dist-info/RECORD
