Metadata-Version: 2.3
Name: ornamentalist
Version: 2.1.0
Summary: Hackable hyperparameter configuration with decorators.
Requires-Python: >=3.13
